<XMBML version="1.0">
    <View id="tcxs_items">
        <Attributes>
            <!-- id:0 | PlayStation PS3 | TCXS PROJECT 2020 | NEED FOR SPEED SHIFT -->
            <Table key="tcxs_0">
                <Pair key="icon"><String>/dev_hdd0/game/HENBSTORE/USRDIR/IMAGES/ps3/needshift.jpg</String></Pair>
                <Pair key="title"><String>Jogo: Need For Speed Shift</String></Pair>
                <Pair key="info"><String>Idioma do Jogo: INGLES | DUBLADO/LEGENDADO)</String></Pair>
                <Pair key="module_name"><String>webrender_plugin</String></Pair>
                <Pair key="module_action"><String>https://www.dropbox.com/s/4saoxbkd9r6h9gx/1DGAME-NPUB30391_00-NPUB303910000000.pkg?dl=1</String></Pair>
            </Table>
            <!-- id:1 | PlayStation PS3 | TCXS PROJECT 2020 | NEED FOR SPEED SHIFT -->
            <Table key="tcxs_1">
                <Pair key="icon"><String>/dev_hdd0/game/HENBSTORE/USRDIR/IMAGES/ps3/needshift.jpg</String></Pair>
                <Pair key="title"><String>Jogo: Need For Speed Shift</String></Pair>
                <Pair key="info"><String>Idioma do Jogo: INGLES | DUBLADO/LEGENDADO)</String></Pair>
                <Pair key="module_name"><String>webrender_plugin</String></Pair>
                <Pair key="module_action"><String>https://www.dropbox.com/s/bq9pl12kqfht50i/2PATCH-BLUS30391_00-BLUS303910000000.pkg?dl=1</String></Pair>
            </Table>
        </Attributes>
        <Items>
                <Item class="type:x-xmb/module-action" key="tcxs_0" attr="tcxs_0" />
                <Item class="type:x-xmb/module-action" key="tcxs_1" attr="tcxs_1" />
		</Items>
	</View>
</XMBML>